py_currency_converter/__init__.py
py_currency_converter/py_exchange_rate.py
py_currency_converter-1.2.0.dist-info/LICENSE
py_currency_converter-1.2.0.dist-info/METADATA
py_currency_converter-1.2.0.dist-info/WHEEL
py_currency_converter-1.2.0.dist-info/top_level.txt
py_currency_converter-1.2.0.dist-info/RECORD
