Metadata-Version: 2.1
Name: py_currency_converter
Version: 1.2.0
Summary: Python Currency Converter
Home-page: https://github.com/catchmaurya/py_currency_converter
Author: Maurya Allimuthu
Author-email: catchmaurya@gmail.com
License: UNKNOWN
Platform: UNKNOWN
Classifier: Programming Language :: Python :: 3
Classifier: License :: OSI Approved :: MIT License
Classifier: Operating System :: OS Independent
